wdlplay/__init__.py
wdlplay/_version.py
wdlplay/wdlplayer.py
wdlplay-0.1.3.dist-info/LICENSE.md
wdlplay-0.1.3.dist-info/METADATA
wdlplay-0.1.3.dist-info/WHEEL
wdlplay-0.1.3.dist-info/top_level.txt
wdlplay-0.1.3.dist-info/RECORD
