Metadata-Version: 2.1
Name: wdlplay
Version: 0.1.3
Summary: Python library for submitting wdl scripts using caper.
Home-page: https://github.com/tarjindersingh/wdlplay
Author: Tarjinder Singh
Author-email: tsingh@broadinstitute.org
License: MIT license
Platform: UNKNOWN
Requires-Python: >=3.7
License-File: LICENSE.md
Requires-Dist: caper (>=2.1.3)
Requires-Dist: autopep8 (==1.5.4)
Requires-Dist: versioneer (>=0.18)
Requires-Dist: logzero (==1.5.0)
Requires-Dist: datatracker (>=0.2.5)
Requires-Dist: findhere (>=0.1.4)
Requires-Dist: slack-sdk
Requires-Dist: hail
